odoo/addons/sale_order_import_packaging/README.rst
odoo/addons/sale_order_import_packaging/__init__.py
odoo/addons/sale_order_import_packaging/__manifest__.py
odoo/addons/sale_order_import_packaging/i18n/es.po
odoo/addons/sale_order_import_packaging/i18n/it.po
odoo/addons/sale_order_import_packaging/i18n/sale_order_import_packaging.pot
odoo/addons/sale_order_import_packaging/i18n/sale_order_packaging_import.pot
odoo/addons/sale_order_import_packaging/models/__init__.py
odoo/addons/sale_order_import_packaging/models/business_document_import.py
odoo/addons/sale_order_import_packaging/readme/CONTRIBUTORS.md
odoo/addons/sale_order_import_packaging/readme/DESCRIPTION.md
odoo/addons/sale_order_import_packaging/static/description/icon.png
odoo/addons/sale_order_import_packaging/static/description/index.html
odoo/addons/sale_order_import_packaging/tests/__init__.py
odoo/addons/sale_order_import_packaging/tests/test_order_line_packaging_import.py
odoo/addons/sale_order_import_packaging/wizard/__init__.py
odoo/addons/sale_order_import_packaging/wizard/sale_order_import.py
odoo_addon_sale_order_import_packaging-18.0.1.0.0.3.dist-info/METADATA
odoo_addon_sale_order_import_packaging-18.0.1.0.0.3.dist-info/WHEEL
odoo_addon_sale_order_import_packaging-18.0.1.0.0.3.dist-info/top_level.txt
odoo_addon_sale_order_import_packaging-18.0.1.0.0.3.dist-info/RECORD
